AUTHORS
LICENSE
MANIFEST.in
README.rst
setup.py
django_friendlyurls.egg-info/PKG-INFO
django_friendlyurls.egg-info/SOURCES.txt
django_friendlyurls.egg-info/dependency_links.txt
django_friendlyurls.egg-info/not-zip-safe
django_friendlyurls.egg-info/top_level.txt
friendlyurls/__init__.py
friendlyurls/admin.py
friendlyurls/models.py
friendlyurls/tests.py
friendlyurls/urls.py
friendlyurls/views.py