Metadata-Version: 1.0
Name: django-friendlyurls
Version: 0.1.1
Summary: Use friendly urls with Django.
Home-page: http://github.com/tachang/django_friendlyurls/
Author: Jeff Tchang
Author-email: jeff.tchang@gmail.com
License: UNKNOWN
Platform: UNKNOWN
Classifier: Development Status :: 4 - Beta
Classifier: Environment :: Web Environment
Classifier: Framework :: Django
Classifier: Intended Audience :: Developers
Classifier: License :: OSI Approved :: BSD License
Classifier: Operating System :: OS Independent
Classifier: Programming Language :: Python
Classifier: Topic :: Utilities
